cronicl/__init__.py
cronicl/_exceptions.py
cronicl/_pipeline.py
cronicl/_queue.py
cronicl/_signals.py
cronicl/timer.py
cronicl/datasets/__init__.py
cronicl/datasets/_datasets.py
cronicl/datasets/_validator.py
cronicl/datasets/io.py
cronicl/interface/__init__.py
cronicl/interface/_http.py
cronicl/operations/__init__.py
cronicl/operations/_common_operations.py
cronicl/operations/_common_sinks.py
cronicl/operations/_messages.py
cronicl/operations/_operation.py
cronicl/operations/_sanitizer.py
cronicl/operations/_trace.py
cronicl-0.1.0.dist-info/METADATA
cronicl-0.1.0.dist-info/WHEEL
cronicl-0.1.0.dist-info/top_level.txt
cronicl-0.1.0.dist-info/RECORD
