Metadata-Version: 2.1
Name: cronicl
Version: 0.1.0
Summary: cronicl is a simple data processing library
Home-page: https://github.com/joocer/cronicl
Author: Joocer
Author-email: justin.joyce@joocer.com
License: UNKNOWN
Platform: UNKNOWN
Requires-Dist: networkx
Requires-Dist: flask
